ckanext/__init__.py
ckanext/restricted_api/__init__.py
ckanext/restricted_api/__version__.py
ckanext/restricted_api/auth.py
ckanext/restricted_api/logic.py
ckanext/restricted_api/mailer.py
ckanext/restricted_api/plugin.py
ckanext/restricted_api/templates/access_granted.txt
ckanext/restricted_api/templates/access_request.txt
ckanext/restricted_api/util.py
ckanext_restricted_api-2.0.6.dist-info/entry_points.txt
ckanext_restricted_api-2.0.6.dist-info/WHEEL
ckanext_restricted_api-2.0.6.dist-info/METADATA
ckanext_restricted_api-2.0.6.dist-info/licenses/LICENSE
ckanext_restricted_api-2.0.6.dist-info/RECORD
