Metadata-Version: 2.1
Name: ckanext-restricted_api
Version: 2.0.6
Summary: Extension to allow dataset restriction via CKAN API.
License: MIT
Keywords: CKAN,restricted,access,authorization,envidat
Author-email: Sam Woodcock <sam.woodcock@protonmail.com>
Requires-Python: >=3.8
Classifier: Programming Language :: Python
Classifier: Programming Language :: Python :: 3 :: Only
Classifier: Programming Language :: Python :: 3.10
Classifier: Programming Language :: Python :: 3.8
Classifier: Programming Language :: Python :: 3.9
Classifier: Topic :: Utilities
Project-URL: documentation, https://envidat.gitlab-pages.wsl.ch/ckanext-restricted_api
Project-URL: homepage, https://gitlabext.wsl.ch/EnviDat/ckanext-restricted_api.git
Project-URL: repository, https://gitlabext.wsl.ch/EnviDat/ckanext-restricted_api.git
